marshmallow_har/__init__.py
marshmallow_har/__version__.py
marshmallow_har/model.py
marshmallow_har/schema.py
marshmallow_har-1.2.1.dist-info/LICENSE
marshmallow_har-1.2.1.dist-info/METADATA
marshmallow_har-1.2.1.dist-info/WHEEL
marshmallow_har-1.2.1.dist-info/top_level.txt
marshmallow_har-1.2.1.dist-info/RECORD
