Metadata-Version: 2.1
Name: marshmallow-har
Version: 1.2.1
Summary: Simple set of marshmallow schemas to load/dump the HTTP Archive (HAR) format.
Home-page: https://github.com/delvelabs/marshmallow-har
Author: Delve Labs inc.
Author-email: info@delvelabs.ca
License: UNKNOWN
Platform: UNKNOWN
Requires-Dist: marshmallow-autoschema (<0.5,>=0.4)
